commandparse/__init__.py
commandparse-1.0.0.dist-info/LICENCE
commandparse-1.0.0.dist-info/METADATA
commandparse-1.0.0.dist-info/WHEEL
commandparse-1.0.0.dist-info/top_level.txt
commandparse-1.0.0.dist-info/zip-safe
commandparse-1.0.0.dist-info/RECORD
