Metadata-Version: 2.1
Name: commandparse
Version: 1.0.0
Summary: CLI application argument parser
Home-page: https://github.com/flgy/commandparse
Author: flgy
Author-email: florian.guilbert@synacktiv.com
License: MIT
Keywords: CLI,command,argparse,parser
Platform: any
Classifier: Development Status :: 4 - Beta
Classifier: Intended Audience :: Information Technology
Classifier: License :: OSI Approved :: MIT License
Classifier: Programming Language :: Python
Classifier: Topic :: Software Development :: Libraries
Classifier: Topic :: Utilities
Classifier: Operating System :: OS Independent
